{
  "main": {
    "id": "5324373015726ba8",
    "type": "split",
    "children": [
      {
        "id": "a105a9aa73e9d5df",
        "type": "tabs",
        "children": [
          {
            "id": "0e7740217c1452d7",
            "type": "leaf",
            "state": {
              "type": "markdown",
              "state": {
                "file": "02 - Knowledge/Computer/CyberSecurity/Networks/Data Flow.md",
                "mode": "source",
                "source": false,
                "backlinks": true,
                "backlinkOpts": {
                  "collapseAll": false,
                  "extraContext": false,
                  "sortOrder": "alphabetical",
                  "showSearch": false,
                  "searchQuery": "",
                  "backlinkCollapsed": false,
                  "unlinkedCollapsed": true
                }
              },
              "icon": "lucide-file",
              "title": "Data Flow"
            }
          }
        ]
      }
    ],
    "direction": "vertical"
  },
  "left": {
    "id": "504dc2811a29fbe7",
    "type": "split",
    "children": [
      {
        "id": "85d70ce88316b252",
        "type": "tabs",
        "children": [
          {
            "id": "ce99a60d5b2a8364",
            "type": "leaf",
            "state": {
              "type": "file-explorer",
              "state": {
                "sortOrder": "alphabetical",
                "autoReveal": false
              },
              "icon": "lucide-folder-closed",
              "title": "Files"
            }
          },
          {
            "id": "f000902d22afaf92",
            "type": "leaf",
            "state": {
              "type": "search",
              "state": {
                "query": "tag:#Przykłady",
                "matchingCase": false,
                "explainSearch": false,
                "collapseAll": false,
                "extraContext": false,
                "sortOrder": "alphabetical"
              },
              "icon": "lucide-search",
              "title": "Szukaj"
            }
          },
          {
            "id": "c0bf0272510b242f",
            "type": "leaf",
            "state": {
              "type": "bookmarks",
              "state": {},
              "icon": "lucide-bookmark",
              "title": "Ulubione"
            }
          },
          {
            "id": "507dc3ce5edef863",
            "type": "leaf",
            "state": {
              "type": "recent-files",
              "state": {},
              "icon": "clock",
              "title": "Recent Files"
            }
          }
        ]
      }
    ],
    "direction": "horizontal",
    "width": 355,
    "collapsed": true
  },
  "right": {
    "id": "62568a0377e7edf7",
    "type": "split",
    "children": [
      {
        "id": "77d5dbc16c5ade8d",
        "type": "tabs",
        "dimension": 65.98837209302326,
        "children": [
          {
            "id": "93e45b047f7a9dfa",
            "type": "leaf",
            "state": {
              "type": "backlink",
              "state": {
                "file": "Markdown Cheatsheat.md",
                "collapseAll": false,
                "extraContext": false,
                "sortOrder": "alphabetical",
                "showSearch": false,
                "searchQuery": "",
                "backlinkCollapsed": false,
                "unlinkedCollapsed": true
              },
              "icon": "links-coming-in",
              "title": "Linki zwrotne do Markdown Cheatsheat"
            }
          },
          {
            "id": "af2b71e1d1ca528f",
            "type": "leaf",
            "state": {
              "type": "tag",
              "state": {
                "sortOrder": "frequency",
                "useHierarchy": true,
                "showSearch": false,
                "searchQuery": ""
              },
              "icon": "lucide-tags",
              "title": "Tags"
            }
          },
          {
            "id": "110d8c871cab0ae6",
            "type": "leaf",
            "state": {
              "type": "outgoing-link",
              "state": {
                "file": "Markdown Cheatsheat.md",
                "linksCollapsed": false,
                "unlinkedCollapsed": true
              },
              "icon": "links-going-out",
              "title": "Łącza wychodzące z Markdown Cheatsheat"
            }
          },
          {
            "id": "9162e94a60fadb6f",
            "type": "leaf",
            "state": {
              "type": "outline",
              "state": {
                "file": "Markdown Cheatsheat.md",
                "followCursor": false,
                "showSearch": false,
                "searchQuery": ""
              },
              "icon": "lucide-list",
              "title": "Konspekt Markdown Cheatsheat"
            }
          },
          {
            "id": "2489a7e0bce6a889",
            "type": "leaf",
            "state": {
              "type": "review-queue-list-view",
              "state": {},
              "icon": "SpacedRepIcon",
              "title": "Notes Review Queue"
            }
          },
          {
            "id": "29e3d9ac8fd90058",
            "type": "leaf",
            "state": {
              "type": "git-view",
              "state": {},
              "icon": "git-pull-request",
              "title": "Source Control"
            }
          }
        ],
        "currentTab": 5
      },
      {
        "id": "3d559545f0b02229",
        "type": "tabs",
        "dimension": 34.01162790697675,
        "children": [
          {
            "id": "525e17f3fd2e1378",
            "type": "leaf",
            "state": {
              "type": "calendar",
              "state": {},
              "icon": "calendar-with-checkmark",
              "title": "Calendar"
            }
          }
        ]
      }
    ],
    "direction": "horizontal",
    "width": 200
  },
  "left-ribbon": {
    "hiddenItems": {
      "obsidian-git:Open Git source control": false,
      "switcher:Open quick switcher": false,
      "canvas:Create new canvas": false,
      "daily-notes:Open today's daily note": false,
      "templates:Insert template": false,
      "command-palette:Open command palette": false,
      "obsidian-spaced-repetition:Review flashcards": false,
      "templater-obsidian:Templater": false,
      "omnisearch:Omnisearch": false,
      "obsidian-excalidraw-plugin:New drawing": false,
      "homepage:Open homepage": false,
      "obsidian-importer:Open Importer": false,
      "obsidian-kanban:Create new board": false,
      "graph:Open graph view": false
    }
  },
  "active": "0e7740217c1452d7",
  "lastOpenFiles": [
    "01_Reference/Pasted image 20250806152212.png",
    "02 - Knowledge/Computer/CyberSecurity/Networks/Firewall i IDS IPS.md",
    "02 - Knowledge/Computer/CyberSecurity/Networks/Data Flow.md",
    "01_Reference/Pasted image 20250806151602.png",
    "01_Reference/Pasted image 20250806151528.png",
    "02 - Knowledge/Computer/CyberSecurity/Networks/Wireless.md",
    "02 - Knowledge/Computer/CyberSecurity/Networks/Firewall i IDS/IPS.md",
    "02 - Knowledge/Computer/CyberSecurity/Networks/Firewall i IDS",
    "02 - Knowledge/Computer/CyberSecurity/Networks/Architektura.md",
    "02 - Knowledge/Computer/CyberSecurity/Networks/Cloud Architecture2.md",
    "02 - Knowledge/Computer/CyberSecurity/Networks/Cloud Architecture.md",
    "02 - Knowledge/Computer/CyberSecurity/Networks/Cloud Architecture1.md",
    "01_Reference/Pasted image 20250806144032.png",
    "00 - Dashboard/HOME.md",
    "01_Reference/Pasted image 20250804161818.png",
    "01_Reference/Pasted image 20250804161652.png",
    "02 - Knowledge/Computer/CyberSecurity/Networks/DNS.md",
    "01_Reference/Pasted image 20250804155931.png",
    "01_Reference/Pasted image 20250804155924.png",
    "02 - Knowledge/Computer/CyberSecurity/Networks/NAT.md",
    "01_Reference/Pasted image 20250804153539.png",
    "02 - Knowledge/Computer/CyberSecurity/Networks/DHCP.md",
    "01_Reference/DORA-3.gif",
    "01_Reference/Pasted image 20250804152750.png",
    "02 - Knowledge/Computer/CyberSecurity/Networks/Komunikacja.md",
    "02 - Knowledge/Computer/CyberSecurity/Networks/Koncepty Sieci.md",
    "02 - Knowledge/Computer/CyberSecurity/Networks/Komponenty.md",
    "02 - Knowledge/Computer/CyberSecurity/Networks/Network Main.md",
    "02 - Knowledge/Computer/CyberSecurity/Networks",
    "02 - Knowledge/Computer/CyberSecurity/CyberSec Main.md",
    "02 - Knowledge/Computer/CyberSecurity/Linux/File Content.md",
    "02 - Knowledge/Computer/CyberSecurity/Linux/Zapory sieciowe.md",
    "02 - Knowledge/Computer/CyberSecurity/Linux/Zabezpieczenia Linux.md",
    "02 - Knowledge/Computer/CyberSecurity/Linux/Logi.md",
    "02 - Knowledge/Computer/CyberSecurity/Linux/Protokoły zdalnego pulpitu.md",
    "02 - Knowledge/Computer/CyberSecurity/Linux/Konfiguracja Sieci.md",
    "02 - Knowledge/Computer/CyberSecurity/Linux/File Managment System.md",
    "02 - Knowledge/Computer/CyberSecurity/Linux/Linux Main.md",
    "Bez nazwy.canvas",
    "01_Reference/linux-commands-cheat-sheet.pdf",
    "04 - References/CheatSheet",
    "04 - References/Courses/HTB",
    "04 - References/Books/Cybersecurity/Linux",
    "04 - References/Books/Cybersecurity",
    "01_Reference",
    "Excalidraw",
    "02 - Knowledge/Computer/CyberSecurity/Linux"
  ]
}